setup.py
douban.fm.egg-info/PKG-INFO
douban.fm.egg-info/SOURCES.txt
douban.fm.egg-info/dependency_links.txt
douban.fm.egg-info/entry_points.txt
douban.fm.egg-info/requires.txt
douban.fm.egg-info/top_level.txt
douban.fm.egg-info/zip-safe
doubanfm/__init__.py
doubanfm/check.py
doubanfm/config.py
doubanfm/data.py
doubanfm/douban.py
doubanfm/exceptions.py
doubanfm/getch.py
doubanfm/lrc2dic.py
doubanfm/model.py
doubanfm/notification.py
doubanfm/player.py
doubanfm/webapi.py
doubanfm/API/__init__.py
doubanfm/API/api.py
doubanfm/API/json_utils.py
doubanfm/API/login.py
doubanfm/API/netease_api.py
doubanfm/colorset/__init__.py
doubanfm/colorset/colors.py
doubanfm/colorset/theme.py
doubanfm/controller/__init__.py
doubanfm/controller/help_controller.py
doubanfm/controller/lrc_controller.py
doubanfm/controller/main_controller.py
doubanfm/controller/manager_controller.py
doubanfm/controller/quit_controller.py
doubanfm/dal/__init__.py
doubanfm/dal/dal_help.py
doubanfm/dal/dal_lrc.py
doubanfm/dal/dal_main.py
doubanfm/dal/dal_manager.py
doubanfm/dal/dal_quit.py
doubanfm/views/__init__.py
doubanfm/views/base_view.py
doubanfm/views/help_view.py
doubanfm/views/history_view.py
doubanfm/views/lrc_view.py
doubanfm/views/main_view.py
doubanfm/views/manager_view.py
doubanfm/views/quit_view.py