Metadata-Version: 1.0
Name: douban.fm
Version: 0.4.14
Summary: a tiny and smart cli player of douban.fm based on Python
Home-page: https://github.com/taizilongxu/douban.fm
Author: taizilongxu
Author-email: 468137306@qq.com
License: MIT
Keywords: python douban douban.fm terminal
Platform: UNKNOWN
